odoo/addons/stock_picking_comment_template/README.rst
odoo/addons/stock_picking_comment_template/__init__.py
odoo/addons/stock_picking_comment_template/__manifest__.py
odoo/addons/stock_picking_comment_template/i18n/de.po
odoo/addons/stock_picking_comment_template/i18n/ja.po
odoo/addons/stock_picking_comment_template/i18n/stock_picking_comment_template.pot
odoo/addons/stock_picking_comment_template/models/__init__.py
odoo/addons/stock_picking_comment_template/models/res_partner.py
odoo/addons/stock_picking_comment_template/models/stock_picking.py
odoo/addons/stock_picking_comment_template/readme/CONTRIBUTORS.rst
odoo/addons/stock_picking_comment_template/readme/DESCRIPTION.rst
odoo/addons/stock_picking_comment_template/security/ir.model.access.csv
odoo/addons/stock_picking_comment_template/static/description/icon.png
odoo/addons/stock_picking_comment_template/static/description/index.html
odoo/addons/stock_picking_comment_template/tests/__init__.py
odoo/addons/stock_picking_comment_template/tests/test_stock_picking_report.py
odoo/addons/stock_picking_comment_template/views/base_comment_template_view.xml
odoo/addons/stock_picking_comment_template/views/report_delivery_document.xml
odoo/addons/stock_picking_comment_template/views/report_picking.xml
odoo/addons/stock_picking_comment_template/views/stock_picking_view.xml
odoo12_addon_stock_picking_comment_template-12.0.1.0.0.99.dev16.dist-info/METADATA
odoo12_addon_stock_picking_comment_template-12.0.1.0.0.99.dev16.dist-info/WHEEL
odoo12_addon_stock_picking_comment_template-12.0.1.0.0.99.dev16.dist-info/top_level.txt
odoo12_addon_stock_picking_comment_template-12.0.1.0.0.99.dev16.dist-info/RECORD
